toolaide/__init__.py
toolaide/cli.py
toolaide/tools/__init__.py
toolaide/tools/common.py
toolaide/tools/list_files.py
toolaide/tools/read_file.py
toolaide/tools/search_files.py
toolaide/tools/write_file.py
toolaide-0.2.0.dist-info/METADATA
toolaide-0.2.0.dist-info/WHEEL
toolaide-0.2.0.dist-info/entry_points.txt
toolaide-0.2.0.dist-info/RECORD
