Metadata-Version: 2.4
Name: toolaide
Version: 0.2.0
Summary: Tool-calling agent for GLM-4.7-Flash-4bit via mlx-lm.server
Project-URL: Homepage, https://github.com/quosa/toolaide
Project-URL: Repository, https://github.com/quosa/toolaide
Author-email: Jussi Kuosa <jussi.kuosa@iki.fi>
License: MIT
Keywords: agent,glm,llm,toolbox
Classifier: Programming Language :: Python :: 3
Classifier: Programming Language :: Python :: 3.10
Classifier: Programming Language :: Python :: 3.11
Classifier: Programming Language :: Python :: 3.12
Requires-Python: >=3.10
Requires-Dist: pathspec
Requires-Dist: requests
Provides-Extra: dev
Requires-Dist: build; extra == 'dev'
Requires-Dist: pytest; extra == 'dev'
Requires-Dist: twine; extra == 'dev'
